Metadata-Version: 2.2
Name: mace-torch
Version: 0.3.12
Home-page: https://github.com/ACEsuit/mace
Classifier: Programming Language :: Python :: 3
Classifier: Operating System :: OS Independent
Classifier: License :: OSI Approved :: MIT License
Requires-Python: >=3.7
License-File: LICENSE.md
Requires-Dist: torch>=1.12
Requires-Dist: e3nn==0.4.4
Requires-Dist: numpy
Requires-Dist: opt_einsum
Requires-Dist: ase
Requires-Dist: torch-ema
Requires-Dist: prettytable
Requires-Dist: matscipy
Requires-Dist: h5py
Requires-Dist: torchmetrics
Requires-Dist: python-hostlist
Requires-Dist: configargparse
Requires-Dist: GitPython
Requires-Dist: pyYAML
Requires-Dist: tqdm
Requires-Dist: lmdb
Requires-Dist: orjson
Requires-Dist: matplotlib
Requires-Dist: pandas
Provides-Extra: wandb
Requires-Dist: wandb; extra == "wandb"
Provides-Extra: fpsample
Requires-Dist: fpsample; extra == "fpsample"
Provides-Extra: dev
Requires-Dist: black; extra == "dev"
Requires-Dist: isort; extra == "dev"
Requires-Dist: mypy; extra == "dev"
Requires-Dist: pre-commit; extra == "dev"
Requires-Dist: pytest; extra == "dev"
Requires-Dist: pytest-benchmark; extra == "dev"
Requires-Dist: pylint; extra == "dev"
Provides-Extra: schedulefree
Requires-Dist: schedulefree; extra == "schedulefree"
Provides-Extra: cueq
Requires-Dist: cuequivariance-torch>=0.2.0; extra == "cueq"
Provides-Extra: cueq-cuda-11
Requires-Dist: cuequivariance-ops-torch-cu11>=0.2.0; extra == "cueq-cuda-11"
Provides-Extra: cueq-cuda-12
Requires-Dist: cuequivariance-ops-torch-cu12>=0.2.0; extra == "cueq-cuda-12"
